{
  "parent": "minecraft:recipes/root",
  "criteria": {
    "has_stucco": {
      "conditions": {
        "items": [
          {
            "items": [
              "verdance:pink_stucco"
            ]
          }
        ]
      },
      "trigger": "minecraft:inventory_changed"
    },
    "has_the_recipe": {
      "conditions": {
        "recipe": "verdance:pink_stucco_slab"
      },
      "trigger": "minecraft:recipe_unlocked"
    }
  },
  "requirements": [
    [
      "has_the_recipe",
      "has_stucco"
    ]
  ],
  "rewards": {
    "recipes": [
      "verdance:pink_stucco_slab"
    ]
  }
}